{"P1": {"labels": ["documentation", "\u6e38\u620f\u8bb0\u5f55"], "postTitle": "\u3010Ghostpia\u3011\u5e7d\u7075\u9547\u7684\u670b\u53cb\u4eec", "postUrl": "post/%E3%80%90Ghostpia%E3%80%91-you-ling-zhen-de-peng-you-men.html", "createdDate": "2024-07-04", "dateLabelColor": "#bc4c00"}, "labelColorDict": {"bug": "#d73a4a", "documentation": "#0075ca", "duplicate": "#cfd3d7", "enhancement": "#a2eeef", "good first issue": "#7057ff", "help wanted": "#008672", "invalid": "#e4e669", "question": "#d876e3", "wontfix": "#ffffff", "\u6e38\u620f\u8bb0\u5f55": "#d4c5f9"}}